colorsplash_common/__init__.py
colorsplash_common/image_ids.py
colorsplash_common/rgb.py
colorsplash_common-0.3.1.dist-info/LICENSE.md
colorsplash_common-0.3.1.dist-info/WHEEL
colorsplash_common-0.3.1.dist-info/METADATA
colorsplash_common-0.3.1.dist-info/RECORD
