Metadata-Version: 2.1
Name: colorsplash-common
Version: 0.3.1
Summary: A common set of classes for the ColorSplash project python components
Home-page: https://thurau.io/colorsplash/
License: MIT
Author: Daniel Thurau
Author-email: daniel.n.thurau@gmail.com
Requires-Python: >=3.8,<4.0
Classifier: License :: OSI Approved :: MIT License
Classifier: Programming Language :: Python :: 3
Classifier: Programming Language :: Python :: 3.10
Classifier: Programming Language :: Python :: 3.8
Classifier: Programming Language :: Python :: 3.9
Requires-Dist: boto3 (>=1.19.3,<2.0.0)
Project-URL: Repository, https://github.com/DanielThurau/colorsplash-common
